{"cameraMode":{"drawMode":0,"name":"Shaded","section":"Shading Mode"},"sceneLighting":true,"audioPlay":false,"sceneViewState":{"showFog":true,"showMaterialUpdate":false,"showSkybox":true,"showFlares":true,"showImageEffects":true,"showParticleSystems":true},"in2DMode":false,"pivot":{"x":1.921731948852539,"y":-1.933728814125061,"z":69.66522216796875},"rotation":{"x":-0.1156371682882309,"y":-0.21805043518543244,"z":0.026029817759990693,"w":-0.9687148928642273},"size":14.914413452148438,"orthographic":false}